QtPy_EqualizerBar/__init__.py
QtPy_EqualizerBar/equalizer_bar/__init__.py
QtPy_EqualizerBar/equalizer_bar/demo.py
QtPy_EqualizerBar/equalizer_bar/equalizer_bar.py
qtpyequalizer-0.1.1.dist-info/licenses/LICENSE
qtpyequalizer-0.1.1.dist-info/METADATA
qtpyequalizer-0.1.1.dist-info/WHEEL
qtpyequalizer-0.1.1.dist-info/top_level.txt
qtpyequalizer-0.1.1.dist-info/RECORD
