Metadata-Version: 2.4
Name: QtPyEqualizer
Version: 0.1.1
Summary: A Qt EqualizerBar widget forked from python-qtwidgets
Author-email: VariousTurtle <leemarvinbeck@gmail.com>
License-Expression: MIT
Project-URL: Homepage, https://github.com/VariousTurtle/qtpy-equalizerbar
Project-URL: Source, https://github.com/VariousTurtle/qtpy-equalizerbar
Requires-Python: >=3.7
License-File: LICENSE
Requires-Dist: qtpy
Dynamic: license-file
